karellen/stack/core/__init__.py
karellen/stack/core/config.py
karellen/stack/core/spi.py
karellen/stack/core/extensions/__init__.py
karellen/stack/core/extensions/installer.py
karellen/stack/core/schema/__init__.py
karellen/stack/core/schema/schemas.py
karellen/stack/core/schema/validation.py
karellen/stack/core/schema/yaml.py
karellen/stack/providers/__init__.py
karellen/stack/providers/loaders.py
karellen/stack/utils/__init__.py
karellen/stack/utils/colors.py
karellen/stack/utils/logging.py
karellen_stack_core-0.0.1.dev20161001024730.dist-info/DESCRIPTION.rst
karellen_stack_core-0.0.1.dev20161001024730.dist-info/METADATA
karellen_stack_core-0.0.1.dev20161001024730.dist-info/RECORD
karellen_stack_core-0.0.1.dev20161001024730.dist-info/WHEEL
karellen_stack_core-0.0.1.dev20161001024730.dist-info/entry_points.txt
karellen_stack_core-0.0.1.dev20161001024730.dist-info/metadata.json
karellen_stack_core-0.0.1.dev20161001024730.dist-info/namespace_packages.txt
karellen_stack_core-0.0.1.dev20161001024730.dist-info/top_level.txt
karellen_stack_core-0.0.1.dev20161001024730.dist-info/zip-safe
