Metadata-Version: 2.0
Name: karellen-stack-core
Version: 0.0.1.dev20161001024730
Summary: karellen-stack-core
Home-page: https://github.com/karellen/karellen-stack-core
Author: Karellen, Inc
Author-email: supervisor@karellen.co
License: Apache License, Version 2.0
Platform: UNKNOWN
Classifier: Development Status :: 5 - Production/Stable
Classifier: Environment :: Console
Classifier: Intended Audience :: Developers
Classifier: License :: OSI Approved :: Apache Software License
Classifier: Programming Language :: Python
Classifier: Programming Language :: Python :: 3.5
Classifier: Topic :: Software Development :: Build Tools
Requires-Dist: jsonmerge (~=1.2.0)
Requires-Dist: jsonschema (~=2.5.0)
Requires-Dist: psutil (~=4.0)
Requires-Dist: pyyaml (~=3.0)
Requires-Dist: setuptools (~=27.0)
Requires-Dist: voluptuous (~=0.9.0)
